dwave-knapsack-solver/setup.py
dwave_knapsack_solver/__init__.py
dwave_knapsack_solver/knapsack_genetic.py
dwave_knapsack_solver-1.1.5.dist-info/LICENSE
dwave_knapsack_solver-1.1.5.dist-info/LICENSE.TXT
dwave_knapsack_solver-1.1.5.dist-info/METADATA
dwave_knapsack_solver-1.1.5.dist-info/WHEEL
dwave_knapsack_solver-1.1.5.dist-info/top_level.txt
dwave_knapsack_solver-1.1.5.dist-info/RECORD
